{
  "subtipo": "locativas",
  "categoria": "subordinativas",
  "definicao": "Indicam lugar (zona cinzenta com pronome relativo)",
  "total": 48,
  "formais": 48,
  "informais": 0,
  "polissemicas": 1,
  "itens": [
    {
      "forma": "onde",
      "registro": "formal_academico",
      "score_academico": 4,
      "polissemica": false
    },
    {
      "forma": "aonde",
      "registro": "formal_academico",
      "score_academico": 4,
      "polissemica": false
    },
    {
      "forma": "donde",
      "registro": "formal_academico",
      "score_academico": 4,
      "polissemica": false
    },
    {
      "forma": "por onde",
      "registro": "formal_academico",
      "score_academico": 4,
      "polissemica": false
    },
    {
      "forma": "até onde",
      "registro": "formal_academico",
      "score_academico": 4,
      "polissemica": false
    },
    {
      "forma": "de onde",
      "registro": "formal_academico",
      "score_academico": 4,
      "polissemica": false
    },
    {
      "forma": "em que (locativo)",
      "registro": "formal_academico",
      "score_academico": 4,
      "polissemica": false
    },
    {
      "forma": "no qual",
      "registro": "formal_academico",
      "score_academico": 4,
      "polissemica": false
    },
    {
      "forma": "na qual",
      "registro": "formal_academico",
      "score_academico": 4,
      "polissemica": false
    },
    {
      "forma": "nos quais",
      "registro": "formal_academico",
      "score_academico": 4,
      "polissemica": false
    },
    {
      "forma": "nas quais",
      "registro": "formal_academico",
      "score_academico": 4,
      "polissemica": false
    },
    {
      "forma": "no lugar em que",
      "registro": "formal_academico",
      "score_academico": 4,
      "polissemica": false
    },
    {
      "forma": "no lugar onde",
      "registro": "formal_academico",
      "score_academico": 4,
      "polissemica": false
    },
    {
      "forma": "no ponto em que",
      "registro": "formal_academico",
      "score_academico": 4,
      "polissemica": false
    },
    {
      "forma": "no sítio em que",
      "registro": "formal_academico",
      "score_academico": 4,
      "polissemica": false
    },
    {
      "forma": "no recanto em que",
      "registro": "formal_academico",
      "score_academico": 4,
      "polissemica": false
    },
    {
      "forma": "no espaço em que",
      "registro": "formal_academico",
      "score_academico": 4,
      "polissemica": false
    },
    {
      "forma": "na região em que",
      "registro": "formal_academico",
      "score_academico": 4,
      "polissemica": false
    },
    {
      "forma": "na área em que",
      "registro": "formal_academico",
      "score_academico": 4,
      "polissemica": false
    },
    {
      "forma": "na zona em que",
      "registro": "formal_academico",
      "score_academico": 4,
      "polissemica": false
    },
    {
      "forma": "no território em que",
      "registro": "formal_academico",
      "score_academico": 4,
      "polissemica": false
    },
    {
      "forma": "no âmbito em que",
      "registro": "formal_academico",
      "score_academico": 4,
      "polissemica": false
    },
    {
      "forma": "no seio de que",
      "registro": "formal_academico",
      "score_academico": 4,
      "polissemica": false
    },
    {
      "forma": "no bojo de que",
      "registro": "formal_academico",
      "score_academico": 4,
      "polissemica": false
    },
    {
      "forma": "no interior em que",
      "registro": "formal_academico",
      "score_academico": 4,
      "polissemica": false
    },
    {
      "forma": "dentro do qual",
      "registro": "formal_academico",
      "score_academico": 4,
      "polissemica": false
    },
    {
      "forma": "fora do qual",
      "registro": "formal_academico",
      "score_academico": 4,
      "polissemica": false
    },
    {
      "forma": "ao redor do qual",
      "registro": "formal_academico",
      "score_academico": 4,
      "polissemica": false
    },
    {
      "forma": "em torno do qual",
      "registro": "formal_academico",
      "score_academico": 4,
      "polissemica": false
    },
    {
      "forma": "às margens de que",
      "registro": "formal_academico",
      "score_academico": 4,
      "polissemica": false
    },
    {
      "forma": "à beira de que",
      "registro": "formal_academico",
      "score_academico": 4,
      "polissemica": true,
      "outros_subtipos": [
        "subordinativas/consecutivas"
      ]
    },
    {
      "forma": "no limiar de que",
      "registro": "formal_academico",
      "score_academico": 4,
      "polissemica": false
    },
    {
      "forma": "no umbral de que",
      "registro": "formal_academico",
      "score_academico": 4,
      "polissemica": false
    },
    {
      "forma": "no vértice em que",
      "registro": "formal_academico",
      "score_academico": 4,
      "polissemica": false
    },
    {
      "forma": "no cerne em que",
      "registro": "formal_academico",
      "score_academico": 4,
      "polissemica": false
    },
    {
      "forma": "no âmago em que",
      "registro": "formal_academico",
      "score_academico": 4,
      "polissemica": false
    },
    {
      "forma": "no entorno de que",
      "registro": "formal_academico",
      "score_academico": 4,
      "polissemica": false
    },
    {
      "forma": "no domínio em que",
      "registro": "formal_academico",
      "score_academico": 4,
      "polissemica": false
    },
    {
      "forma": "no recesso em que",
      "registro": "formal_academico",
      "score_academico": 4,
      "polissemica": false
    },
    {
      "forma": "no recôndito em que",
      "registro": "formal_academico",
      "score_academico": 4,
      "polissemica": false
    },
    {
      "forma": "na paragem em que",
      "registro": "formal_academico",
      "score_academico": 4,
      "polissemica": false
    },
    {
      "forma": "no sopé de que",
      "registro": "formal_academico",
      "score_academico": 4,
      "polissemica": false
    },
    {
      "forma": "no cume em que",
      "registro": "formal_academico",
      "score_academico": 4,
      "polissemica": false
    },
    {
      "forma": "no horizonte em que",
      "registro": "formal_academico",
      "score_academico": 4,
      "polissemica": false
    },
    {
      "forma": "no ponto cardeal em que",
      "registro": "formal_academico",
      "score_academico": 4,
      "polissemica": false
    },
    {
      "forma": "lá onde",
      "registro": "formal_academico",
      "score_academico": 4,
      "polissemica": false
    },
    {
      "forma": "aqui onde",
      "registro": "formal_academico",
      "score_academico": 4,
      "polissemica": false
    },
    {
      "forma": "ali onde",
      "registro": "formal_academico",
      "score_academico": 4,
      "polissemica": false
    }
  ]
}