{
  "subtipo": "proporcionais",
  "categoria": "subordinativas",
  "definicao": "Indicam proporção ou progressão simultânea",
  "total": 43,
  "formais": 43,
  "informais": 0,
  "polissemicas": 5,
  "itens": [
    {
      "forma": "à medida que",
      "registro": "formal_academico",
      "score_academico": 4,
      "polissemica": false
    },
    {
      "forma": "à proporção que",
      "registro": "formal_academico",
      "score_academico": 4,
      "polissemica": false
    },
    {
      "forma": "ao passo que",
      "registro": "formal_academico",
      "score_academico": 4,
      "polissemica": true,
      "outros_subtipos": [
        "coordenativas/adversativas"
      ]
    },
    {
      "forma": "conforme",
      "registro": "formal_academico",
      "score_academico": 4,
      "polissemica": true,
      "outros_subtipos": [
        "subordinativas/conformativas",
        "subordinativas/modais"
      ]
    },
    {
      "forma": "quanto mais... mais",
      "registro": "formal_academico",
      "score_academico": 4,
      "polissemica": false
    },
    {
      "forma": "quanto menos... menos",
      "registro": "formal_academico",
      "score_academico": 4,
      "polissemica": false
    },
    {
      "forma": "quanto mais... menos",
      "registro": "formal_academico",
      "score_academico": 4,
      "polissemica": false
    },
    {
      "forma": "quanto menos... mais",
      "registro": "formal_academico",
      "score_academico": 4,
      "polissemica": false
    },
    {
      "forma": "tanto mais... quanto",
      "registro": "formal_academico",
      "score_academico": 4,
      "polissemica": false
    },
    {
      "forma": "tanto menos... quanto",
      "registro": "formal_academico",
      "score_academico": 4,
      "polissemica": false
    },
    {
      "forma": "ao tempo que",
      "registro": "formal_academico",
      "score_academico": 4,
      "polissemica": true,
      "outros_subtipos": [
        "subordinativas/temporais"
      ]
    },
    {
      "forma": "enquanto (proporcional)",
      "registro": "formal_academico",
      "score_academico": 4,
      "polissemica": false
    },
    {
      "forma": "na mesma medida em que",
      "registro": "formal_academico",
      "score_academico": 4,
      "polissemica": false
    },
    {
      "forma": "na mesma proporção em que",
      "registro": "formal_academico",
      "score_academico": 4,
      "polissemica": false
    },
    {
      "forma": "em igual medida a que",
      "registro": "formal_academico",
      "score_academico": 4,
      "polissemica": false
    },
    {
      "forma": "pari passu com",
      "registro": "formal_academico",
      "score_academico": 4,
      "polissemica": false
    },
    {
      "forma": "no compasso em que",
      "registro": "formal_academico",
      "score_academico": 4,
      "polissemica": false
    },
    {
      "forma": "no ritmo em que",
      "registro": "formal_academico",
      "score_academico": 4,
      "polissemica": false
    },
    {
      "forma": "no diapasão de que",
      "registro": "formal_academico",
      "score_academico": 4,
      "polissemica": true,
      "outros_subtipos": [
        "subordinativas/modais"
      ]
    },
    {
      "forma": "no mesmo passo em que",
      "registro": "formal_academico",
      "score_academico": 4,
      "polissemica": false
    },
    {
      "forma": "à razão de que",
      "registro": "formal_academico",
      "score_academico": 4,
      "polissemica": false
    },
    {
      "forma": "em razão direta de",
      "registro": "formal_academico",
      "score_academico": 4,
      "polissemica": false
    },
    {
      "forma": "em razão inversa de",
      "registro": "formal_academico",
      "score_academico": 4,
      "polissemica": false
    },
    {
      "forma": "proporcionalmente a que",
      "registro": "formal_academico",
      "score_academico": 4,
      "polissemica": false
    },
    {
      "forma": "em escala crescente a",
      "registro": "formal_academico",
      "score_academico": 4,
      "polissemica": false
    },
    {
      "forma": "em escala decrescente a",
      "registro": "formal_academico",
      "score_academico": 4,
      "polissemica": false
    },
    {
      "forma": "crescendo... cresce",
      "registro": "formal_academico",
      "score_academico": 4,
      "polissemica": false
    },
    {
      "forma": "diminuindo... diminui",
      "registro": "formal_academico",
      "score_academico": 4,
      "polissemica": false
    },
    {
      "forma": "enquanto mais",
      "registro": "formal_academico",
      "score_academico": 4,
      "polissemica": false
    },
    {
      "forma": "tanto quanto mais",
      "registro": "formal_academico",
      "score_academico": 4,
      "polissemica": false
    },
    {
      "forma": "acompanhando que",
      "registro": "formal_academico",
      "score_academico": 4,
      "polissemica": true,
      "outros_subtipos": [
        "subordinativas/conformativas"
      ]
    },
    {
      "forma": "em paralelo crescente com",
      "registro": "formal_academico",
      "score_academico": 4,
      "polissemica": false
    },
    {
      "forma": "em paralelo decrescente com",
      "registro": "formal_academico",
      "score_academico": 4,
      "polissemica": false
    },
    {
      "forma": "no mesmo fluxo de",
      "registro": "formal_academico",
      "score_academico": 4,
      "polissemica": false
    },
    {
      "forma": "na mesma onda de",
      "registro": "formal_academico",
      "score_academico": 4,
      "polissemica": false
    },
    {
      "forma": "espelhando o avanço de",
      "registro": "formal_academico",
      "score_academico": 4,
      "polissemica": false
    },
    {
      "forma": "no pari com",
      "registro": "formal_academico",
      "score_academico": 4,
      "polissemica": false
    },
    {
      "forma": "na curva de que",
      "registro": "formal_academico",
      "score_academico": 4,
      "polissemica": false
    },
    {
      "forma": "na trajetória de que",
      "registro": "formal_academico",
      "score_academico": 4,
      "polissemica": false
    },
    {
      "forma": "em gradação com",
      "registro": "formal_academico",
      "score_academico": 4,
      "polissemica": false
    },
    {
      "forma": "em graduação com",
      "registro": "formal_academico",
      "score_academico": 4,
      "polissemica": false
    },
    {
      "forma": "em progressão a",
      "registro": "formal_academico",
      "score_academico": 4,
      "polissemica": false
    },
    {
      "forma": "em regressão a",
      "registro": "formal_academico",
      "score_academico": 4,
      "polissemica": false
    }
  ]
}